stacklib/Stack.py
stacklib/__innit__.py
stacklib-0.1.4.dist-info/licenses/LICENSE
stacklib-0.1.4.dist-info/METADATA
stacklib-0.1.4.dist-info/WHEEL
stacklib-0.1.4.dist-info/top_level.txt
stacklib-0.1.4.dist-info/RECORD
