Metadata-Version: 2.4
Name: stacklib
Version: 0.1.4
Summary: A chainable stack-based utility library
Author: NovaStar
License: MIT
Requires-Python: >=3.8
License-File: LICENSE
Dynamic: license-file
